cryptohftdata/__init__.py
cryptohftdata/client.py
cryptohftdata/data_types.py
cryptohftdata/exceptions.py
cryptohftdata/exchanges.py
cryptohftdata/http_client.py
cryptohftdata/models.py
cryptohftdata/utils.py
cryptohftdata-0.1.8.dist-info/licenses/LICENSE
cryptohftdata-0.1.8.dist-info/METADATA
cryptohftdata-0.1.8.dist-info/WHEEL
cryptohftdata-0.1.8.dist-info/top_level.txt
cryptohftdata-0.1.8.dist-info/RECORD
